LICENSE
README.md
setup.py
runpynb/__init__.py
runpynb/runpynb.py
runpynb.egg-info/PKG-INFO
runpynb.egg-info/SOURCES.txt
runpynb.egg-info/dependency_links.txt
runpynb.egg-info/requires.txt
runpynb.egg-info/top_level.txt
runpynb/scripts/runpynb