Metadata-Version: 2.1
Name: runpynb
Version: 0.1.1
Summary: Run (and time) Jupyter Notebooks for command-line and makefile
Home-page: https://github.com/lsys/runPyNB
Author: Lucas Shen
Author-email: lucas@lucasshen.com
Maintainer: Lucas Shen
Maintainer-email: lucas@lucasshen.com
License: MIT
Keywords: jupyter notebook,jupyter,command-line,makefile,make,nbconvert
Platform: UNKNOWN
Classifier: License :: OSI Approved :: MIT License
Classifier: Natural Language :: English
Classifier: Programming Language :: Python :: 3
Classifier: Programming Language :: Python :: 3.6
Classifier: Programming Language :: Python :: 3.7
Classifier: Programming Language :: Python :: 3.8
Classifier: Programming Language :: Python :: 3.9
Classifier: Programming Language :: Python :: 3.10
License-File: LICENSE
